spa2num/__init__.py
spa2num/converter.py
spa2num-0.0.6.dist-info/LICENSE.txt
spa2num-0.0.6.dist-info/METADATA
spa2num-0.0.6.dist-info/WHEEL
spa2num-0.0.6.dist-info/top_level.txt
spa2num-0.0.6.dist-info/RECORD
