Metadata-Version: 2.1
Name: spa2num
Version: 0.0.6
Summary: Spanish word converter to numerical digits
Home-page: https://github.com/cartovarc/spa2num
Author: Carlos Tovar
License: MIT
Keywords: spanish,words,converter,numeric,digits
Platform: UNKNOWN
Classifier: Environment :: Console
Classifier: Development Status :: 1 - Planning
Classifier: Intended Audience :: Developers
Classifier: Topic :: Text Processing :: Linguistic
Classifier: Topic :: Software Development :: Libraries :: Python Modules
Classifier: Programming Language :: Python :: 3
Classifier: License :: OSI Approved :: GNU Library or Lesser General Public License (LGPL)
Requires-Dist: num2words
